altflags/__init__.py
altflags/flags.py
altflags-0.0.3.dist-info/LICENSE
altflags-0.0.3.dist-info/METADATA
altflags-0.0.3.dist-info/WHEEL
altflags-0.0.3.dist-info/top_level.txt
altflags-0.0.3.dist-info/RECORD
