Metadata-Version: 2.1
Name: altflags
Version: 0.0.3
Summary: Python alternative (binary) flags
Home-page: UNKNOWN
Author: Oddity
License: MIT
Platform: UNKNOWN
Classifier: Programming Language :: Python :: 3
Classifier: License :: OSI Approved :: MIT License
Classifier: Operating System :: OS Independent
Requires-Python: >=3.8.0
License-File: LICENSE
